cbr_xyz/__init__.py
cbr_xyz/utils/Version.py
cbr_xyz/utils/__init__.py
cbr_xyz/version
cbr_xyz-0.8.0.dist-info/LICENSE
cbr_xyz-0.8.0.dist-info/METADATA
cbr_xyz-0.8.0.dist-info/WHEEL
cbr_xyz-0.8.0.dist-info/RECORD
