Metadata-Version: 2.1
Name: cbr_xyz
Version: 0.8.0
Summary: CBR - XYZ
Home-page: https://github.com/the-cyber-boardroom/cbr-xyz
License: MIT
Author: Dinis Cruz
Author-email: dinis.cruz@owasp.org
Requires-Python: >=3.7,<4.0
Classifier: License :: OSI Approved :: MIT License
Classifier: Programming Language :: Python :: 3
Classifier: Programming Language :: Python :: 3.7
Classifier: Programming Language :: Python :: 3.8
Classifier: Programming Language :: Python :: 3.9
Classifier: Programming Language :: Python :: 3.10
Classifier: Programming Language :: Python :: 3.11
Classifier: Programming Language :: Python :: 3.12
Requires-Dist: osbot-utils
Project-URL: Repository, https://github.com/the-cyber-boardroom/cbr-xyz
